decaf/api/client/__init__.py
decaf/api/client/_internal.py
decaf/api/client/machinery.py
decaf/api/client/py.typed
decaf/api/client/types.py
decaf/api/client/utils.py
decaf_api_client-0.0.12.dist-info/LICENSE
decaf_api_client-0.0.12.dist-info/METADATA
decaf_api_client-0.0.12.dist-info/WHEEL
decaf_api_client-0.0.12.dist-info/top_level.txt
decaf_api_client-0.0.12.dist-info/RECORD
