Metadata-Version: 2.1
Name: decaf-api-client
Version: 0.0.12
Summary: DECAF API Client
Author-email: Vehbi Sinan Tunalioglu <vst@vsthost.com>
Maintainer-email: Vehbi Sinan Tunalioglu <vst@vsthost.com>
License: Copyright (2017-2019) Vehbi Sinan Tunalioglu.
Project-URL: homepage, https://github.com/telostat/decaf-api-client-python
Project-URL: documentation, https://github.com/telostat/decaf-api-client-python
Project-URL: repository, https://github.com/telostat/decaf-api-client-python
Project-URL: changelog, https://github.com/teloscube/decaf-client-python/blob/main/CHANGELOG.md
Keywords: decaf,api,client,finance
Classifier: Development Status :: 3 - Alpha
Classifier: Intended Audience :: Developers
Classifier: License :: OSI Approved :: BSD License
Classifier: Programming Language :: Python :: 3
Classifier: Programming Language :: Python :: 3.10
Classifier: Programming Language :: Python :: 3.11
Classifier: Programming Language :: Python :: 3.12
Requires-Python: >=3.10
License-File: LICENSE
Requires-Dist: pydantic <3,>=2
Requires-Dist: requests <3,>=2
Provides-Extra: dev
Requires-Dist: build ; extra == 'dev'
Requires-Dist: ipython ; extra == 'dev'
Requires-Dist: pip ; extra == 'dev'
Requires-Dist: pyls-flake8 ; extra == 'dev'
Requires-Dist: pyls-isort ; extra == 'dev'
Requires-Dist: pylsp-mypy ; extra == 'dev'
Requires-Dist: pylsp-rope ; extra == 'dev'
Requires-Dist: python-lsp-black ; extra == 'dev'
Requires-Dist: python-lsp-server ; extra == 'dev'
Requires-Dist: rope ; extra == 'dev'
Requires-Dist: twine ; extra == 'dev'
Requires-Dist: wheel ; extra == 'dev'
Provides-Extra: test
Requires-Dist: black ; extra == 'test'
Requires-Dist: flake8 ; extra == 'test'
Requires-Dist: isort ; extra == 'test'
Requires-Dist: mypy ; extra == 'test'
Requires-Dist: pytest ; extra == 'test'
Requires-Dist: types-requests ; extra == 'test'
